README.md
setup.py
whistlepy/__init__.py
whistlepy/__init__.pyc
whistlepy/constants.py
whistlepy/exceptions.py
whistlepy/utils.py
whistlepy.egg-info/PKG-INFO
whistlepy.egg-info/SOURCES.txt
whistlepy.egg-info/dependency_links.txt
whistlepy.egg-info/not-zip-safe
whistlepy.egg-info/requires.txt
whistlepy.egg-info/top_level.txt
whistlepy/client/__init__.py
whistlepy/client/base.py
whistlepy/client/api/__init__.py
whistlepy/client/api/adhoc.py
whistlepy/client/api/auth.py
whistlepy/client/api/base.py
whistlepy/client/api/geo.py
whistlepy/client/api/label.py
whistlepy/client/api/notification.py
whistlepy/client/api/oauth.py
whistlepy/client/api/organization.py
whistlepy/client/api/post.py
whistlepy/client/api/score.py
whistlepy/session/__init__.py
whistlepy/session/memcachedstorage.py
whistlepy/session/memorystorage.py
whistlepy/session/redisstorage.py
whistlepy/session/shovestorage.py