Metadata-Version: 1.0
Name: whistlepy
Version: 0.1.1
Summary: whistle sdk
Home-page: https://github.com/atuple/whistlepy
Author: sai
Author-email: 3030159@qq.com
License: MIT
Keywords: whistle,SDK,weishao
Platform: UNKNOWN
